pdf2pptx/__init__.py
pdf2pptx/cli.py
pdf2pptx_fix-1.0.5.2.dist-info/licenses/LICENSE
pdf2pptx_fix-1.0.5.2.dist-info/METADATA
pdf2pptx_fix-1.0.5.2.dist-info/WHEEL
pdf2pptx_fix-1.0.5.2.dist-info/entry_points.txt
pdf2pptx_fix-1.0.5.2.dist-info/top_level.txt
pdf2pptx_fix-1.0.5.2.dist-info/RECORD
