Metadata-Version: 2.4
Name: pdf2pptx-fix
Version: 1.0.5.2
Summary: Utility to convert a PDF slideshow to Powerpoint PPTX.
Home-page: https://github.com/doctorixx/pdf2pptx-fix
Author: Kevin McGuinness
Author-email: genius@doctorixx.ru
License: MIT
Classifier: Development Status :: 4 - Beta
Classifier: Programming Language :: Python
Classifier: Programming Language :: Python :: 3
Classifier: Programming Language :: Python :: 3.6
Classifier: Environment :: Console
Classifier: License :: OSI Approved :: MIT License
Classifier: Topic :: Utilities
Classifier: Topic :: Multimedia :: Graphics :: Presentation
License-File: LICENSE
Requires-Dist: pymupdf
Requires-Dist: python-pptx
Requires-Dist: click
Requires-Dist: tqdm
Dynamic: author
Dynamic: author-email
Dynamic: classifier
Dynamic: description
Dynamic: description-content-type
Dynamic: home-page
Dynamic: license
Dynamic: license-file
Dynamic: requires-dist
Dynamic: summary
